NaaVRE_workflow_jupyterlab/__init__.py
NaaVRE_workflow_jupyterlab/_version.py
naavre_workflow_jupyterlab-0.4.11.data/data/share/jupyter/labextensions/@naavre/workflow-jupyterlab/package.json
naavre_workflow_jupyterlab-0.4.11.data/data/share/jupyter/labextensions/@naavre/workflow-jupyterlab/schemas/@naavre/workflow-jupyterlab/package.json.orig
naavre_workflow_jupyterlab-0.4.11.data/data/share/jupyter/labextensions/@naavre/workflow-jupyterlab/schemas/@naavre/workflow-jupyterlab/plugin.json
naavre_workflow_jupyterlab-0.4.11.data/data/share/jupyter/labextensions/@naavre/workflow-jupyterlab/static/108.48b2ba5d3630c07b2f73.js
naavre_workflow_jupyterlab-0.4.11.data/data/share/jupyter/labextensions/@naavre/workflow-jupyterlab/static/108.48b2ba5d3630c07b2f73.js.LICENSE.txt
naavre_workflow_jupyterlab-0.4.11.data/data/share/jupyter/labextensions/@naavre/workflow-jupyterlab/static/160.73a46663a12f71fd1eb2.js
naavre_workflow_jupyterlab-0.4.11.data/data/share/jupyter/labextensions/@naavre/workflow-jupyterlab/static/162.43e8b83fb48516a3c6e0.js
naavre_workflow_jupyterlab-0.4.11.data/data/share/jupyter/labextensions/@naavre/workflow-jupyterlab/static/291.ccf1ccc71f94261e498c.js
naavre_workflow_jupyterlab-0.4.11.data/data/share/jupyter/labextensions/@naavre/workflow-jupyterlab/static/293.8eaa4f79b95d0c339de5.js
naavre_workflow_jupyterlab-0.4.11.data/data/share/jupyter/labextensions/@naavre/workflow-jupyterlab/static/293.8eaa4f79b95d0c339de5.js.LICENSE.txt
naavre_workflow_jupyterlab-0.4.11.data/data/share/jupyter/labextensions/@naavre/workflow-jupyterlab/static/353.0150fd6a2797a060c363.js
naavre_workflow_jupyterlab-0.4.11.data/data/share/jupyter/labextensions/@naavre/workflow-jupyterlab/static/436.8f5cd4199468372bc404.js
naavre_workflow_jupyterlab-0.4.11.data/data/share/jupyter/labextensions/@naavre/workflow-jupyterlab/static/436.8f5cd4199468372bc404.js.LICENSE.txt
naavre_workflow_jupyterlab-0.4.11.dist-info/METADATA
naavre_workflow_jupyterlab-0.4.11.dist-info/WHEEL
naavre_workflow_jupyterlab-0.4.11.dist-info/licenses/LICENSE
naavre_workflow_jupyterlab-0.4.11.dist-info/RECORD
